mercadolibre/Client.py
mercadolibre/MercadoLibreAPI.py
mercadolibre/OAuth.py
mercadolibre/__init__.py
mercadolibre/enums/HttpMethods.py
mercadolibre/enums/HttpStatusCode.py
mercadolibre/enums/__init__.py
mercadolibre/enums/paths.py
mercadolibre/resources/Item.py
mercadolibre/resources/Order.py
mercadolibre/resources/Question.py
mercadolibre/resources/__init__.py
mercadolibre_client-0.0.1.dist-info/LICENCE
mercadolibre_client-0.0.1.dist-info/METADATA
mercadolibre_client-0.0.1.dist-info/WHEEL
mercadolibre_client-0.0.1.dist-info/top_level.txt
mercadolibre_client-0.0.1.dist-info/RECORD
