Metadata-Version: 2.1
Name: mercadolibre-client
Version: 0.0.1
Summary: Mercado Libre API Client (unoffical)
Home-page: https://github.com/mercadoradar/mercadolibre-client
Author: Mercado Radar
Author-email: contato@mercadoradar.com.br
License: UNKNOWN
Project-URL: Bug Tracker, https://github.com/mercadoradar/mercadolibre-client/issues
Platform: UNKNOWN
Classifier: Programming Language :: Python :: 3
Classifier: License :: OSI Approved :: MIT License
Classifier: Operating System :: OS Independent
Requires-Python: >=3.8
License-File: LICENCE
